{"ID":100006,"Key":"02ed26e20f17e41e607f19d6e76c4f2ac9b02cfab5a773ff19497912a0f246d5","Raw":"250625212839837178000501094458","Audit":{"CreatedAt":"2025-06-25T21:28:39.837181+01:00","CreatedBy":"sys_service","CreatedOn":"orion","CreatedAtDisplay":"2025-06-25 21:28:39","Updates":[{"UpdatedAt":"2025-06-25T21:28:39.837181+01:00","UpdateAction":"CREA","UpdatedBy":"sys_service","UpdatedOn":"orion","UpdatedAtDisplay":"2025-06-25 21:28:39","UpdateNotes":"New User created massUser9373@example.com"},{"UpdatedAt":"2025-06-25T21:28:40.02616+01:00","UpdateAction":"DELE","UpdatedBy":"sys_service","UpdatedOn":"orion","UpdatedAtDisplay":"2025-06-25 21:28:40","UpdateNotes":"Clearing User 100006 @ initialisation "}],"DeletedAt":"2025-06-25T21:28:40.02616+01:00","DeletedBy":"sys_service","DeletedOn":"orion","DeletedAtDisplay":"2025-06-25 21:28:40","AuditSequence":2,"DBVersion":1},"Username":"massUser9373","Email":"massUser9373@example.com","PasswordHash":"Test 9373"}