{"ID":100014,"Key":"e84e8dbd5245be6f8b0372649d83a549d8400aa2163f6811ba393754ce99f256","Raw":"250626100501514188000501062030","Audit":{"CreatedAt":"2025-06-26T10:05:01.514192+01:00","CreatedBy":"sys_service","CreatedOn":"orion","CreatedAtDisplay":"2025-06-26 10:05:01","Updates":[{"UpdatedAt":"2025-06-26T10:05:01.514192+01:00","UpdateAction":"CREA","UpdatedBy":"sys_service","UpdatedOn":"orion","UpdatedAtDisplay":"2025-06-26 10:05:01","UpdateNotes":"New User created massUser2446@example.com"},{"UpdatedAt":"2025-06-26T10:05:06.371325+01:00","UpdateAction":"GRAN","UpdatedBy":"sys_service","UpdatedOn":"orion","UpdatedAtDisplay":"2025-06-26 10:05:06","UpdateNotes":"Job Processing"},{"UpdatedAt":"2025-06-26T10:05:06.625045+01:00","UpdateAction":"GRAN","UpdatedBy":"sys_service","UpdatedOn":"orion","UpdatedAtDisplay":"2025-06-26 10:05:06","UpdateNotes":"Job Processing"},{"UpdatedAt":"2025-06-26T10:05:55.25408+01:00","UpdateAction":"DELE","UpdatedBy":"sys_service","UpdatedOn":"orion","UpdatedAtDisplay":"2025-06-26 10:05:55","UpdateNotes":"Clearing User 100014 @ initialisation "}],"DeletedAt":"2025-06-26T10:05:55.25408+01:00","DeletedBy":"sys_service","DeletedOn":"orion","DeletedAtDisplay":"2025-06-26 10:05:55","AuditSequence":6,"DBVersion":1},"Username":"massUser2446","Email":"massUser2446@example.com","PasswordHash":"Test 2446"}