{"ID":100011,"Key":"2ba6ec247c3d7fa582014882fdab4d65b8800a31a2ba958f85025689ca292c4a","Raw":"250626101336642698000501030895","Audit":{"CreatedAt":"2025-06-26T10:13:36.642703+01:00","CreatedBy":"sys_service","CreatedOn":"orion","CreatedAtDisplay":"2025-06-26 10:13:36","Updates":[{"UpdatedAt":"2025-06-26T10:13:36.642703+01:00","UpdateAction":"CREA","UpdatedBy":"sys_service","UpdatedOn":"orion","UpdatedAtDisplay":"2025-06-26 10:13:36","UpdateNotes":"New User created massUser7624@example.com"},{"UpdatedAt":"2025-06-26T10:13:42.373643+01:00","UpdateAction":"GRAN","UpdatedBy":"sys_service","UpdatedOn":"orion","UpdatedAtDisplay":"2025-06-26 10:13:42","UpdateNotes":"Job Processing"},{"UpdatedAt":"2025-06-26T10:13:44.559064+01:00","UpdateAction":"GRAN","UpdatedBy":"sys_service","UpdatedOn":"orion","UpdatedAtDisplay":"2025-06-26 10:13:44","UpdateNotes":"Job Processing"},{"UpdatedAt":"2025-06-26T10:15:22.806773+01:00","UpdateAction":"DELE","UpdatedBy":"sys_service","UpdatedOn":"orion","UpdatedAtDisplay":"2025-06-26 10:15:22","UpdateNotes":"Clearing User 100011 @ initialisation "}],"DeletedAt":"2025-06-26T10:15:22.806773+01:00","DeletedBy":"sys_service","DeletedOn":"orion","DeletedAtDisplay":"2025-06-26 10:15:22","AuditSequence":6,"DBVersion":1},"Username":"massUser7624","Email":"massUser7624@example.com","PasswordHash":"Test 7624"}