{"ID":100020,"Key":"6fbabfc73edfc923fcf26ea5e2753da1b3c8851b3c23d1b1dc934cbe673ca414","Raw":"250626120444577908000501051127","Audit":{"CreatedAt":"2025-06-26T12:04:44.577922+01:00","CreatedBy":"sys_service","CreatedOn":"orion","CreatedAtDisplay":"2025-06-26 12:04:44","Updates":[{"UpdatedAt":"2025-06-26T12:04:44.577922+01:00","UpdateAction":"CREA","UpdatedBy":"sys_service","UpdatedOn":"orion","UpdatedAtDisplay":"2025-06-26 12:04:44","UpdateNotes":"New User created massUser1110@example.com"}],"DeletedAt":"0001-01-01T00:00:00Z","DeletedBy":"","DeletedOn":"","DeletedAtDisplay":"","AuditSequence":1,"DBVersion":1},"Username":"massUser1110","Email":"massUser1110@example.com","PasswordHash":"Test 1110"}