{"ID":100018,"Key":"a11d647bb135e98f04386f7b6bc41167f0b3498cb9a059c3cc61e8aac1ffa238","Raw":"250626101049489771000501046719","Audit":{"CreatedAt":"2025-06-26T10:10:49.489775+01:00","CreatedBy":"sys_service","CreatedOn":"orion","CreatedAtDisplay":"2025-06-26 10:10:49","Updates":[{"UpdatedAt":"2025-06-26T10:10:49.489775+01:00","UpdateAction":"CREA","UpdatedBy":"sys_service","UpdatedOn":"orion","UpdatedAtDisplay":"2025-06-26 10:10:49","UpdateNotes":"New User created massUser6453@example.com"},{"UpdatedAt":"2025-06-26T10:10:55.12431+01:00","UpdateAction":"GRAN","UpdatedBy":"sys_service","UpdatedOn":"orion","UpdatedAtDisplay":"2025-06-26 10:10:55","UpdateNotes":"Job Processing"},{"UpdatedAt":"2025-06-26T10:10:55.32809+01:00","UpdateAction":"GRAN","UpdatedBy":"sys_service","UpdatedOn":"orion","UpdatedAtDisplay":"2025-06-26 10:10:55","UpdateNotes":"Job Processing"},{"UpdatedAt":"2025-06-26T10:11:58.32167+01:00","UpdateAction":"DELE","UpdatedBy":"sys_service","UpdatedOn":"orion","UpdatedAtDisplay":"2025-06-26 10:11:58","UpdateNotes":"Clearing User 100018 @ initialisation "}],"DeletedAt":"2025-06-26T10:11:58.32167+01:00","DeletedBy":"sys_service","DeletedOn":"orion","DeletedAtDisplay":"2025-06-26 10:11:58","AuditSequence":6,"DBVersion":1},"Username":"massUser6453","Email":"massUser6453@example.com","PasswordHash":"Test 6453"}