{"ID":100000,"Key":"86bd558e779b7f46b19445f22db1a8b788427042a230575475a193f9509b93a4","Raw":"250626101049056529000501070839","Audit":{"CreatedAt":"2025-06-26T10:10:49.056538+01:00","CreatedBy":"sys_service","CreatedOn":"orion","CreatedAtDisplay":"2025-06-26 10:10:49","Updates":[{"UpdatedAt":"2025-06-26T10:10:49.056538+01:00","UpdateAction":"CREA","UpdatedBy":"sys_service","UpdatedOn":"orion","UpdatedAtDisplay":"2025-06-26 10:10:49","UpdateNotes":"New User created massUser5711@example.com"},{"UpdatedAt":"2025-06-26T10:10:49.186405+01:00","UpdateAction":"DELE","UpdatedBy":"sys_service","UpdatedOn":"orion","UpdatedAtDisplay":"2025-06-26 10:10:49","UpdateNotes":"Clearing User 100000 @ initialisation "}],"DeletedAt":"2025-06-26T10:10:49.186405+01:00","DeletedBy":"sys_service","DeletedOn":"orion","DeletedAtDisplay":"2025-06-26 10:10:49","AuditSequence":2,"DBVersion":1},"Username":"massUser5711","Email":"massUser5711@example.com","PasswordHash":"Test 5711"}