{"ID":100011,"Key":"ac124d6818950b0911da2b728101f6ffd9d9b5d5310fe7a28f4b0da03ef83c96","Raw":"250626100943826769000501030895","Audit":{"CreatedAt":"2025-06-26T10:09:43.826777+01:00","CreatedBy":"sys_service","CreatedOn":"orion","CreatedAtDisplay":"2025-06-26 10:09:43","Updates":[{"UpdatedAt":"2025-06-26T10:09:43.826777+01:00","UpdateAction":"CREA","UpdatedBy":"sys_service","UpdatedOn":"orion","UpdatedAtDisplay":"2025-06-26 10:09:43","UpdateNotes":"New User created massUser1246@example.com"},{"UpdatedAt":"2025-06-26T10:10:48.437933+01:00","UpdateAction":"DELE","UpdatedBy":"sys_service","UpdatedOn":"orion","UpdatedAtDisplay":"2025-06-26 10:10:48","UpdateNotes":"Clearing User 100011 @ initialisation "}],"DeletedAt":"2025-06-26T10:10:48.437933+01:00","DeletedBy":"sys_service","DeletedOn":"orion","DeletedAtDisplay":"2025-06-26 10:10:48","AuditSequence":2,"DBVersion":1},"Username":"massUser1246","Email":"massUser1246@example.com","PasswordHash":"Test 1246"}