{"ID":100007,"Key":"68ebace5154f8d7c4ea2aab8aec514697d25f146c195c699d6df806623a967f9","Raw":"250626115629544348000501095069","Audit":{"CreatedAt":"2025-06-26T11:56:29.54435+01:00","CreatedBy":"sys_service","CreatedOn":"orion","CreatedAtDisplay":"2025-06-26 11:56:29","Updates":[{"UpdatedAt":"2025-06-26T11:56:29.54435+01:00","UpdateAction":"CREA","UpdatedBy":"sys_service","UpdatedOn":"orion","UpdatedAtDisplay":"2025-06-26 11:56:29","UpdateNotes":"New User created massUser2173@example.com"},{"UpdatedAt":"2025-06-26T11:56:29.749117+01:00","UpdateAction":"DELE","UpdatedBy":"sys_service","UpdatedOn":"orion","UpdatedAtDisplay":"2025-06-26 11:56:29","UpdateNotes":"Clearing User 100007 @ initialisation "}],"DeletedAt":"2025-06-26T11:56:29.749117+01:00","DeletedBy":"sys_service","DeletedOn":"orion","DeletedAtDisplay":"2025-06-26 11:56:29","AuditSequence":2,"DBVersion":1},"Username":"massUser2173","Email":"massUser2173@example.com","PasswordHash":"Test 2173"}