{"ID":116,"Key":"7fe9f7b755f32224fbd7a3923f70badf5473043cb6b2ee06e3772a72cf2827b9","Raw":"250920193850275117000501047529","Audit":{"CreatedAt":"2025-09-20T19:38:50.275242+01:00","CreatedBy":"sys_service","CreatedOn":"orion","CreatedAtDisplay":"2025-09-20 19:38:50","Updates":[{"UpdatedAt":"2025-09-20T19:38:50.275242+01:00","UpdateAction":"CREA","UpdatedBy":"sys_service","UpdatedOn":"orion","UpdatedAtDisplay":"2025-09-20 19:38:50","UpdateNotes":"New weight created 100"}],"DeletedAt":"0001-01-01T00:00:00Z","DeletedBy":"","DeletedOn":"","DeletedAtDisplay":"","AuditSequence":1,"DBVersion":1},"UserID":100,"RecordedAt":"2024-11-29T00:00:00Z","Weight":{"value":127.5},"BMI":{"value":36.1,"text":"Obese","glyph":"🔴","external":36.1},"Note":"Imported Weight:127.50 kg Loss:6.00 kg"}